anibridge_anilist_provider/__init__.py
anibridge_anilist_provider/client.py
anibridge_anilist_provider/list.py
anibridge_anilist_provider/models.py
anibridge_anilist_provider-0.1.2.dist-info/WHEEL
anibridge_anilist_provider-0.1.2.dist-info/METADATA
anibridge_anilist_provider-0.1.2.dist-info/RECORD
